[
  {
    "round": 1,
    "phase": 1,
    "table": null,
    "winner": -1,
    "player1": "aiueoniisan"
  },
  {
    "round": 1,
    "phase": 1,
    "table": null,
    "winner": -1,
    "player1": "disposablehero"
  },
  {
    "round": 1,
    "phase": 1,
    "table": null,
    "winner": -1,
    "player1": "lakzy"
  },
  {
    "round": 1,
    "phase": 1,
    "table": null,
    "winner": -1,
    "player1": "danimal"
  },
  {
    "round": 1,
    "phase": 1,
    "table": null,
    "winner": -1,
    "player1": "flipinton"
  },
  {
    "round": 1,
    "phase": 1,
    "table": null,
    "winner": -1,
    "player1": "russ_ii"
  },
  {
    "round": 1,
    "phase": 1,
    "table": null,
    "winner": -1,
    "player1": "griffsama"
  },
  {
    "round": 1,
    "phase": 1,
    "table": null,
    "winner": -1,
    "player1": "bingka"
  },
  {
    "round": 1,
    "phase": 1,
    "table": null,
    "winner": -1,
    "player1": "bobby02"
  },
  {
    "round": 1,
    "phase": 1,
    "table": 1,
    "winner": "waterbetter",
    "player1": "waterbetter",
    "player2": "irid1um"
  },
  {
    "round": 1,
    "phase": 1,
    "table": 2,
    "winner": "hiiran",
    "player1": "hiiran",
    "player2": "ttv_jmpm9"
  },
  {
    "round": 1,
    "phase": 1,
    "table": 3,
    "winner": "soadmon",
    "player1": "3ki99",
    "player2": "soadmon"
  },
  {
    "round": 1,
    "phase": 1,
    "table": 4,
    "winner": "julez45",
    "player1": "bigred12121",
    "player2": "julez45"
  },
  {
    "round": 1,
    "phase": 1,
    "table": 5,
    "winner": "vagabondwolf",
    "player1": "vagabondwolf",
    "player2": "draxoz"
  },
  {
    "round": 1,
    "phase": 1,
    "table": 6,
    "winner": "luffyhouz",
    "player1": "popay",
    "player2": "luffyhouz"
  },
  {
    "round": 1,
    "phase": 1,
    "table": 7,
    "winner": "piutonium",
    "player1": "maykol2294",
    "player2": "piutonium"
  },
  {
    "round": 1,
    "phase": 1,
    "table": 8,
    "winner": "juggynaut14",
    "player1": "noah2000",
    "player2": "juggynaut14"
  },
  {
    "round": 1,
    "phase": 1,
    "table": 9,
    "winner": "n3wa",
    "player1": "xavikush6",
    "player2": "n3wa"
  },
  {
    "round": 1,
    "phase": 1,
    "table": 10,
    "winner": "wxxsz",
    "player1": "wxxsz",
    "player2": "quetzalyami"
  },
  {
    "round": 1,
    "phase": 1,
    "table": 11,
    "winner": "yuuichi",
    "player1": "sotrill18",
    "player2": "yuuichi"
  },
  {
    "round": 1,
    "phase": 1,
    "table": 12,
    "winner": "val22",
    "player1": "val22",
    "player2": "estehlegitea"
  },
  {
    "round": 1,
    "phase": 1,
    "table": 13,
    "winner": "zakaryan08",
    "player1": "lightxz",
    "player2": "zakaryan08"
  },
  {
    "round": 1,
    "phase": 1,
    "table": 14,
    "winner": "alonso39",
    "player1": "alonso39",
    "player2": "meendes"
  },
  {
    "round": 1,
    "phase": 1,
    "table": 15,
    "winner": "ixerox",
    "player1": "ixerox",
    "player2": "raiderboy181"
  },
  {
    "round": 1,
    "phase": 1,
    "table": 16,
    "winner": "donkindonuts",
    "player1": "donkindonuts",
    "player2": "luckypoke"
  },
  {
    "round": 1,
    "phase": 1,
    "table": 17,
    "winner": "ezz67",
    "player1": "ezz67",
    "player2": "torapapa"
  },
  {
    "round": 1,
    "phase": 1,
    "table": 18,
    "winner": "ojisanathee",
    "player1": "ojisanathee",
    "player2": "wildnacatl"
  },
  {
    "round": 1,
    "phase": 1,
    "table": 19,
    "winner": "nyphyx",
    "player1": "nyphyx",
    "player2": "raydorm"
  },
  {
    "round": 1,
    "phase": 1,
    "table": 20,
    "winner": "cus",
    "player1": "victorssito",
    "player2": "cus"
  },
  {
    "round": 1,
    "phase": 1,
    "table": 21,
    "winner": "eilix524",
    "player1": "eilix524",
    "player2": "flaneurx"
  },
  {
    "round": 1,
    "phase": 1,
    "table": 22,
    "winner": "raiden_shogun14",
    "player1": "moky2510",
    "player2": "raiden_shogun14"
  },
  {
    "round": 1,
    "phase": 1,
    "table": 23,
    "winner": "tibandera",
    "player1": "hanaex",
    "player2": "tibandera"
  },
  {
    "round": 1,
    "phase": 1,
    "table": 24,
    "winner": "sparadrap",
    "player1": "tapatio94",
    "player2": "sparadrap"
  },
  {
    "round": 1,
    "phase": 1,
    "table": 25,
    "winner": "alana",
    "player1": "super_peace",
    "player2": "alana"
  },
  {
    "round": 1,
    "phase": 1,
    "table": 26,
    "winner": "goblinsama",
    "player1": "shikamaru_br",
    "player2": "goblinsama"
  },
  {
    "round": 1,
    "phase": 1,
    "table": 27,
    "winner": "asura_wakr",
    "player1": "asura_wakr",
    "player2": "nakopol91"
  },
  {
    "round": 1,
    "phase": 1,
    "table": 28,
    "winner": "zholit",
    "player1": "aoisora",
    "player2": "zholit"
  },
  {
    "round": 1,
    "phase": 1,
    "table": 29,
    "winner": "valhar",
    "player1": "wompwomp007",
    "player2": "valhar"
  },
  {
    "round": 1,
    "phase": 1,
    "table": 30,
    "winner": "esdeath",
    "player1": "muswa",
    "player2": "esdeath"
  },
  {
    "round": 1,
    "phase": 1,
    "table": 31,
    "winner": "hosi",
    "player1": "turbone101",
    "player2": "hosi"
  },
  {
    "round": 1,
    "phase": 1,
    "table": 32,
    "winner": "gaizkita",
    "player1": "roshy",
    "player2": "gaizkita"
  },
  {
    "round": 1,
    "phase": 1,
    "table": 33,
    "winner": "elmatadorperu",
    "player1": "elmatadorperu",
    "player2": "rzlby"
  },
  {
    "round": 1,
    "phase": 1,
    "table": 34,
    "winner": "specs",
    "player1": "siro",
    "player2": "specs"
  },
  {
    "round": 1,
    "phase": 1,
    "table": 35,
    "winner": -1,
    "player1": "pokehunter01",
    "player2": "feherlac"
  },
  {
    "round": 1,
    "phase": 1,
    "table": 36,
    "winner": "zeekholz",
    "player1": "elatomico",
    "player2": "zeekholz"
  },
  {
    "round": 1,
    "phase": 1,
    "table": 37,
    "winner": "iplaypokemans",
    "player1": "isanpum",
    "player2": "iplaypokemans"
  },
  {
    "round": 1,
    "phase": 1,
    "table": 38,
    "winner": "portlandpoliwags",
    "player1": "portlandpoliwags",
    "player2": "bredle"
  },
  {
    "round": 1,
    "phase": 1,
    "table": 39,
    "winner": "yu_handes",
    "player1": "luci",
    "player2": "yu_handes"
  },
  {
    "round": 1,
    "phase": 1,
    "table": 40,
    "winner": "warpis",
    "player1": "warpis",
    "player2": "ppitopin8"
  },
  {
    "round": 1,
    "phase": 1,
    "table": 41,
    "winner": "njjord7",
    "player1": "njjord7",
    "player2": "nandosgude"
  },
  {
    "round": 1,
    "phase": 1,
    "table": 42,
    "winner": "dashmd",
    "player1": "dashmd",
    "player2": "frogger"
  },
  {
    "round": 1,
    "phase": 1,
    "table": 43,
    "winner": "ycha_00",
    "player1": "ycha_00",
    "player2": "neonox40"
  },
  {
    "round": 1,
    "phase": 1,
    "table": 44,
    "winner": "roky",
    "player1": "sinorci200",
    "player2": "roky"
  },
  {
    "round": 1,
    "phase": 1,
    "table": 45,
    "winner": "senkokuroline26",
    "player1": "sawatz_1503",
    "player2": "senkokuroline26"
  },
  {
    "round": 1,
    "phase": 1,
    "table": 46,
    "winner": "vgckomalika",
    "player1": "srafaelitocs",
    "player2": "vgckomalika"
  },
  {
    "round": 1,
    "phase": 1,
    "table": 47,
    "winner": "cloud77",
    "player1": "cloud77",
    "player2": "hectordf"
  },
  {
    "round": 1,
    "phase": 1,
    "table": 48,
    "winner": "nemu",
    "player1": "nemu",
    "player2": "king_solomon"
  },
  {
    "round": 1,
    "phase": 1,
    "table": 49,
    "winner": "hakomatotaco",
    "player1": "hakomatotaco"
  },
  {
    "round": 2,
    "phase": 1,
    "table": 1,
    "winner": "ezz67",
    "player1": "hakomatotaco",
    "player2": "ezz67"
  },
  {
    "round": 2,
    "phase": 1,
    "table": 2,
    "winner": "vgckomalika",
    "player1": "vgckomalika",
    "player2": "juggynaut14"
  },
  {
    "round": 2,
    "phase": 1,
    "table": 3,
    "winner": "cus",
    "player1": "cus",
    "player2": "luffyhouz"
  },
  {
    "round": 2,
    "phase": 1,
    "table": 4,
    "winner": "iplaypokemans",
    "player1": "wxxsz",
    "player2": "iplaypokemans"
  },
  {
    "round": 2,
    "phase": 1,
    "table": 5,
    "winner": "val22",
    "player1": "raiden_shogun14",
    "player2": "val22"
  },
  {
    "round": 2,
    "phase": 1,
    "table": 6,
    "winner": "julez45",
    "player1": "julez45",
    "player2": "senkokuroline26"
  },
  {
    "round": 2,
    "phase": 1,
    "table": 7,
    "winner": "warpis",
    "player1": "donkindonuts",
    "player2": "warpis"
  },
  {
    "round": 2,
    "phase": 1,
    "table": 8,
    "winner": "esdeath",
    "player1": "zeekholz",
    "player2": "esdeath"
  },
  {
    "round": 2,
    "phase": 1,
    "table": 9,
    "winner": "cloud77",
    "player1": "cloud77",
    "player2": "elmatadorperu"
  },
  {
    "round": 2,
    "phase": 1,
    "table": 10,
    "winner": "hiiran",
    "player1": "hiiran",
    "player2": "ycha_00"
  },
  {
    "round": 2,
    "phase": 1,
    "table": 11,
    "winner": "dashmd",
    "player1": "dashmd",
    "player2": "specs"
  },
  {
    "round": 2,
    "phase": 1,
    "table": 12,
    "winner": "hosi",
    "player1": "hosi",
    "player2": "nyphyx"
  },
  {
    "round": 2,
    "phase": 1,
    "table": 13,
    "winner": "soadmon",
    "player1": "vagabondwolf",
    "player2": "soadmon"
  },
  {
    "round": 2,
    "phase": 1,
    "table": 14,
    "winner": "waterbetter",
    "player1": "waterbetter",
    "player2": "zholit"
  },
  {
    "round": 2,
    "phase": 1,
    "table": 15,
    "winner": "roky",
    "player1": "sparadrap",
    "player2": "roky"
  },
  {
    "round": 2,
    "phase": 1,
    "table": 16,
    "winner": "portlandpoliwags",
    "player1": "gaizkita",
    "player2": "portlandpoliwags"
  },
  {
    "round": 2,
    "phase": 1,
    "table": 17,
    "winner": "asura_wakr",
    "player1": "asura_wakr",
    "player2": "zakaryan08"
  },
  {
    "round": 2,
    "phase": 1,
    "table": 18,
    "winner": "tibandera",
    "player1": "n3wa",
    "player2": "tibandera"
  },
  {
    "round": 2,
    "phase": 1,
    "table": 19,
    "winner": "yuuichi",
    "player1": "yuuichi",
    "player2": "piutonium"
  },
  {
    "round": 2,
    "phase": 1,
    "table": 20,
    "winner": "nemu",
    "player1": "nemu",
    "player2": "yu_handes"
  },
  {
    "round": 2,
    "phase": 1,
    "table": 21,
    "winner": "njjord7",
    "player1": "goblinsama",
    "player2": "njjord7"
  },
  {
    "round": 2,
    "phase": 1,
    "table": 22,
    "winner": "valhar",
    "player1": "eilix524",
    "player2": "valhar"
  },
  {
    "round": 2,
    "phase": 1,
    "table": 23,
    "winner": "ixerox",
    "player1": "ixerox",
    "player2": "alana"
  },
  {
    "round": 2,
    "phase": 1,
    "table": 24,
    "winner": "ojisanathee",
    "player1": "ojisanathee",
    "player2": "alonso39"
  },
  {
    "round": 2,
    "phase": 1,
    "table": 25,
    "winner": "bigred12121",
    "player1": "bigred12121",
    "player2": "maykol2294"
  },
  {
    "round": 2,
    "phase": 1,
    "table": 26,
    "winner": "wompwomp007",
    "player1": "quetzalyami",
    "player2": "wompwomp007"
  },
  {
    "round": 2,
    "phase": 1,
    "table": 27,
    "winner": "raydorm",
    "player1": "raydorm",
    "player2": "raiderboy181"
  },
  {
    "round": 2,
    "phase": 1,
    "table": 28,
    "winner": "draxoz",
    "player1": "muswa",
    "player2": "draxoz"
  },
  {
    "round": 2,
    "phase": 1,
    "table": 29,
    "winner": "bingka",
    "player1": "isanpum",
    "player2": "bingka"
  },
  {
    "round": 2,
    "phase": 1,
    "table": 30,
    "winner": "aoisora",
    "player1": "aoisora",
    "player2": "pokehunter01"
  },
  {
    "round": 2,
    "phase": 1,
    "table": 31,
    "winner": "siro",
    "player1": "flipinton",
    "player2": "siro"
  },
  {
    "round": 2,
    "phase": 1,
    "table": 32,
    "winner": "tapatio94",
    "player1": "tapatio94",
    "player2": "frogger"
  },
  {
    "round": 2,
    "phase": 1,
    "table": 33,
    "winner": "sawatz_1503",
    "player1": "sawatz_1503",
    "player2": "xavikush6"
  },
  {
    "round": 2,
    "phase": 1,
    "table": 34,
    "winner": "hectordf",
    "player1": "hectordf",
    "player2": "ttv_jmpm9"
  },
  {
    "round": 2,
    "phase": 1,
    "table": 35,
    "winner": "shikamaru_br",
    "player1": "popay",
    "player2": "shikamaru_br"
  },
  {
    "round": 2,
    "phase": 1,
    "table": 36,
    "winner": "elatomico",
    "player1": "elatomico",
    "player2": "noah2000"
  },
  {
    "round": 2,
    "phase": 1,
    "table": 37,
    "winner": "wildnacatl",
    "player1": "neonox40",
    "player2": "wildnacatl"
  },
  {
    "round": 2,
    "phase": 1,
    "table": 38,
    "winner": "nakopol91",
    "player1": "rzlby",
    "player2": "nakopol91"
  },
  {
    "round": 2,
    "phase": 1,
    "table": 39,
    "winner": "bredle",
    "player1": "irid1um",
    "player2": "bredle"
  },
  {
    "round": 2,
    "phase": 1,
    "table": 40,
    "winner": "disposablehero",
    "player1": "king_solomon",
    "player2": "disposablehero"
  },
  {
    "round": 2,
    "phase": 1,
    "table": 41,
    "winner": "aiueoniisan",
    "player1": "torapapa",
    "player2": "aiueoniisan"
  },
  {
    "round": 2,
    "phase": 1,
    "table": 42,
    "winner": "turbone101",
    "player1": "turbone101",
    "player2": "meendes"
  },
  {
    "round": 2,
    "phase": 1,
    "table": 43,
    "winner": "russ_ii",
    "player1": "ppitopin8",
    "player2": "russ_ii"
  },
  {
    "round": 2,
    "phase": 1,
    "table": 44,
    "winner": "roshy",
    "player1": "roshy",
    "player2": "luckypoke"
  },
  {
    "round": 2,
    "phase": 1,
    "table": 45,
    "winner": "nandosgude",
    "player1": "sinorci200",
    "player2": "nandosgude"
  },
  {
    "round": 2,
    "phase": 1,
    "table": 46,
    "winner": "3ki99",
    "player1": "danimal",
    "player2": "3ki99"
  },
  {
    "round": 2,
    "phase": 1,
    "table": 47,
    "winner": "griffsama",
    "player1": "griffsama",
    "player2": "flaneurx"
  },
  {
    "round": 2,
    "phase": 1,
    "table": 48,
    "winner": "estehlegitea",
    "player1": "estehlegitea",
    "player2": "srafaelitocs"
  },
  {
    "round": 2,
    "phase": 1,
    "table": 49,
    "winner": "hanaex",
    "player1": "sotrill18",
    "player2": "hanaex"
  },
  {
    "round": 2,
    "phase": 1,
    "table": 50,
    "winner": "lightxz",
    "player1": "lightxz",
    "player2": "luci"
  },
  {
    "round": 2,
    "phase": 1,
    "table": 51,
    "winner": "super_peace",
    "player1": "super_peace"
  },
  {
    "round": 3,
    "phase": 1,
    "table": 1,
    "winner": "vgckomalika",
    "player1": "cloud77",
    "player2": "vgckomalika"
  },
  {
    "round": 3,
    "phase": 1,
    "table": 2,
    "winner": "esdeath",
    "player1": "esdeath",
    "player2": "iplaypokemans"
  },
  {
    "round": 3,
    "phase": 1,
    "table": 3,
    "winner": "ixerox",
    "player1": "ixerox",
    "player2": "waterbetter"
  },
  {
    "round": 3,
    "phase": 1,
    "table": 4,
    "winner": "cus",
    "player1": "julez45",
    "player2": "cus"
  },
  {
    "round": 3,
    "phase": 1,
    "table": 5,
    "winner": "ojisanathee",
    "player1": "val22",
    "player2": "ojisanathee"
  },
  {
    "round": 3,
    "phase": 1,
    "table": 6,
    "winner": "valhar",
    "player1": "hiiran",
    "player2": "valhar"
  },
  {
    "round": 3,
    "phase": 1,
    "table": 7,
    "winner": "asura_wakr",
    "player1": "tibandera",
    "player2": "asura_wakr"
  },
  {
    "round": 3,
    "phase": 1,
    "table": 8,
    "winner": "yuuichi",
    "player1": "yuuichi",
    "player2": "soadmon"
  },
  {
    "round": 3,
    "phase": 1,
    "table": 9,
    "winner": "dashmd",
    "player1": "dashmd",
    "player2": "roky"
  },
  {
    "round": 3,
    "phase": 1,
    "table": 10,
    "winner": "nemu",
    "player1": "njjord7",
    "player2": "nemu"
  },
  {
    "round": 3,
    "phase": 1,
    "table": 11,
    "winner": "portlandpoliwags",
    "player1": "portlandpoliwags",
    "player2": "warpis"
  },
  {
    "round": 3,
    "phase": 1,
    "table": 12,
    "winner": "hosi",
    "player1": "hosi",
    "player2": "ezz67"
  },
  {
    "round": 3,
    "phase": 1,
    "table": 13,
    "winner": "nyphyx",
    "player1": "nyphyx",
    "player2": "super_peace"
  },
  {
    "round": 3,
    "phase": 1,
    "table": 14,
    "winner": "goblinsama",
    "player1": "goblinsama",
    "player2": "draxoz"
  },
  {
    "round": 3,
    "phase": 1,
    "table": 15,
    "winner": "donkindonuts",
    "player1": "donkindonuts",
    "player2": "zeekholz"
  },
  {
    "round": 3,
    "phase": 1,
    "table": 16,
    "winner": "raiden_shogun14",
    "player1": "gaizkita",
    "player2": "raiden_shogun14"
  },
  {
    "round": 3,
    "phase": 1,
    "table": 17,
    "winner": "sparadrap",
    "player1": "siro",
    "player2": "sparadrap"
  },
  {
    "round": 3,
    "phase": 1,
    "table": 18,
    "winner": "wompwomp007",
    "player1": "wildnacatl",
    "player2": "wompwomp007"
  },
  {
    "round": 3,
    "phase": 1,
    "table": 19,
    "winner": "hectordf",
    "player1": "estehlegitea",
    "player2": "hectordf"
  },
  {
    "round": 3,
    "phase": 1,
    "table": 20,
    "winner": "senkokuroline26",
    "player1": "n3wa",
    "player2": "senkokuroline26"
  },
  {
    "round": 3,
    "phase": 1,
    "table": 21,
    "winner": "raydorm",
    "player1": "raydorm",
    "player2": "luffyhouz"
  },
  {
    "round": 3,
    "phase": 1,
    "table": 22,
    "winner": "hakomatotaco",
    "player1": "zakaryan08",
    "player2": "hakomatotaco"
  },
  {
    "round": 3,
    "phase": 1,
    "table": 23,
    "winner": "sawatz_1503",
    "player1": "sawatz_1503",
    "player2": "shikamaru_br"
  },
  {
    "round": 3,
    "phase": 1,
    "table": 24,
    "winner": "bingka",
    "player1": "tapatio94",
    "player2": "bingka"
  },
  {
    "round": 3,
    "phase": 1,
    "table": 25,
    "winner": "piutonium",
    "player1": "piutonium",
    "player2": "3ki99"
  },
  {
    "round": 3,
    "phase": 1,
    "table": 26,
    "winner": "bredle",
    "player1": "bigred12121",
    "player2": "bredle"
  },
  {
    "round": 3,
    "phase": 1,
    "table": 27,
    "winner": "lightxz",
    "player1": "zholit",
    "player2": "lightxz"
  },
  {
    "round": 3,
    "phase": 1,
    "table": 28,
    "winner": "elmatadorperu",
    "player1": "roshy",
    "player2": "elmatadorperu"
  },
  {
    "round": 3,
    "phase": 1,
    "table": 29,
    "winner": "turbone101",
    "player1": "turbone101",
    "player2": "alana"
  },
  {
    "round": 3,
    "phase": 1,
    "table": 30,
    "winner": "nandosgude",
    "player1": "nandosgude",
    "player2": "hanaex"
  },
  {
    "round": 3,
    "phase": 1,
    "table": 31,
    "winner": "wxxsz",
    "player1": "wxxsz",
    "player2": "disposablehero"
  },
  {
    "round": 3,
    "phase": 1,
    "table": 32,
    "winner": "vagabondwolf",
    "player1": "russ_ii",
    "player2": "vagabondwolf"
  },
  {
    "round": 3,
    "phase": 1,
    "table": 33,
    "winner": "eilix524",
    "player1": "juggynaut14",
    "player2": "eilix524"
  },
  {
    "round": 3,
    "phase": 1,
    "table": 34,
    "winner": "aoisora",
    "player1": "aoisora",
    "player2": "griffsama"
  },
  {
    "round": 3,
    "phase": 1,
    "table": 35,
    "winner": "nakopol91",
    "player1": "specs",
    "player2": "nakopol91"
  },
  {
    "round": 3,
    "phase": 1,
    "table": 36,
    "winner": "elatomico",
    "player1": "alonso39",
    "player2": "elatomico"
  },
  {
    "round": 3,
    "phase": 1,
    "table": 37,
    "winner": "meendes",
    "player1": "meendes",
    "player2": "king_solomon"
  },
  {
    "round": 3,
    "phase": 1,
    "table": 38,
    "winner": "raiderboy181",
    "player1": "raiderboy181",
    "player2": "ttv_jmpm9"
  },
  {
    "round": 3,
    "phase": 1,
    "table": 39,
    "winner": -1,
    "player1": "torapapa",
    "player2": "rzlby"
  },
  {
    "round": 3,
    "phase": 1,
    "table": 40,
    "winner": "srafaelitocs",
    "player1": "maykol2294",
    "player2": "srafaelitocs"
  },
  {
    "round": 3,
    "phase": 1,
    "table": 41,
    "winner": "luckypoke",
    "player1": "luckypoke",
    "player2": "ppitopin8"
  },
  {
    "round": 3,
    "phase": 1,
    "table": 42,
    "winner": "popay",
    "player1": "popay",
    "player2": "pokehunter01"
  },
  {
    "round": 3,
    "phase": 1,
    "table": 43,
    "winner": "quetzalyami",
    "player1": "quetzalyami",
    "player2": "flipinton"
  },
  {
    "round": 3,
    "phase": 1,
    "table": 44,
    "winner": "sotrill18",
    "player1": "frogger",
    "player2": "sotrill18"
  },
  {
    "round": 3,
    "phase": 1,
    "table": 45,
    "winner": "irid1um",
    "player1": "irid1um",
    "player2": "noah2000"
  },
  {
    "round": 3,
    "phase": 1,
    "table": 46,
    "winner": "muswa",
    "player1": "muswa",
    "player2": "xavikush6"
  },
  {
    "round": 4,
    "phase": 1,
    "table": 1,
    "winner": "portlandpoliwags",
    "player1": "portlandpoliwags",
    "player2": "cus"
  },
  {
    "round": 4,
    "phase": 1,
    "table": 2,
    "winner": "yuuichi",
    "player1": "asura_wakr",
    "player2": "yuuichi"
  },
  {
    "round": 4,
    "phase": 1,
    "table": 3,
    "winner": "ojisanathee",
    "player1": "dashmd",
    "player2": "ojisanathee"
  },
  {
    "round": 4,
    "phase": 1,
    "table": 4,
    "winner": "vgckomalika",
    "player1": "vgckomalika",
    "player2": "nemu"
  },
  {
    "round": 4,
    "phase": 1,
    "table": 5,
    "winner": "hosi",
    "player1": "esdeath",
    "player2": "hosi"
  },
  {
    "round": 4,
    "phase": 1,
    "table": 6,
    "winner": "ixerox",
    "player1": "ixerox",
    "player2": "valhar"
  },
  {
    "round": 4,
    "phase": 1,
    "table": 7,
    "winner": "wompwomp007",
    "player1": "sparadrap",
    "player2": "wompwomp007"
  },
  {
    "round": 4,
    "phase": 1,
    "table": 8,
    "winner": "waterbetter",
    "player1": "piutonium",
    "player2": "waterbetter"
  },
  {
    "round": 4,
    "phase": 1,
    "table": 9,
    "winner": "sawatz_1503",
    "player1": "sawatz_1503",
    "player2": "val22"
  },
  {
    "round": 4,
    "phase": 1,
    "table": 10,
    "winner": "njjord7",
    "player1": "nyphyx",
    "player2": "njjord7"
  },
  {
    "round": 4,
    "phase": 1,
    "table": 11,
    "winner": "wxxsz",
    "player1": "wxxsz",
    "player2": "raydorm"
  },
  {
    "round": 4,
    "phase": 1,
    "table": 12,
    "winner": "aoisora",
    "player1": "warpis",
    "player2": "aoisora"
  },
  {
    "round": 4,
    "phase": 1,
    "table": 13,
    "winner": "elmatadorperu",
    "player1": "hakomatotaco",
    "player2": "elmatadorperu"
  },
  {
    "round": 4,
    "phase": 1,
    "table": 14,
    "winner": "eilix524",
    "player1": "ezz67",
    "player2": "eilix524"
  },
  {
    "round": 4,
    "phase": 1,
    "table": 15,
    "winner": "tibandera",
    "player1": "tibandera",
    "player2": "raiden_shogun14"
  },
  {
    "round": 4,
    "phase": 1,
    "table": 16,
    "winner": "julez45",
    "player1": "roky",
    "player2": "julez45"
  },
  {
    "round": 4,
    "phase": 1,
    "table": 17,
    "winner": "bingka",
    "player1": "bingka",
    "player2": "donkindonuts"
  },
  {
    "round": 4,
    "phase": 1,
    "table": 18,
    "winner": "hectordf",
    "player1": "hectordf",
    "player2": "goblinsama"
  },
  {
    "round": 4,
    "phase": 1,
    "table": 19,
    "winner": "soadmon",
    "player1": "soadmon",
    "player2": "cloud77"
  },
  {
    "round": 4,
    "phase": 1,
    "table": 20,
    "winner": "vagabondwolf",
    "player1": "hiiran",
    "player2": "vagabondwolf"
  },
  {
    "round": 4,
    "phase": 1,
    "table": 21,
    "winner": "turbone101",
    "player1": "elatomico",
    "player2": "turbone101"
  },
  {
    "round": 4,
    "phase": 1,
    "table": 22,
    "winner": "lightxz",
    "player1": "lightxz",
    "player2": "bredle"
  },
  {
    "round": 4,
    "phase": 1,
    "table": 23,
    "winner": "nandosgude",
    "player1": "senkokuroline26",
    "player2": "nandosgude"
  },
  {
    "round": 4,
    "phase": 1,
    "table": 24,
    "winner": "iplaypokemans",
    "player1": "iplaypokemans",
    "player2": "nakopol91"
  },
  {
    "round": 4,
    "phase": 1,
    "table": 25,
    "winner": "meendes",
    "player1": "meendes",
    "player2": "sotrill18"
  },
  {
    "round": 4,
    "phase": 1,
    "table": 26,
    "winner": "raiderboy181",
    "player1": "raiderboy181",
    "player2": "muswa"
  },
  {
    "round": 4,
    "phase": 1,
    "table": 27,
    "winner": "shikamaru_br",
    "player1": "shikamaru_br",
    "player2": "3ki99"
  },
  {
    "round": 4,
    "phase": 1,
    "table": 28,
    "winner": "specs",
    "player1": "super_peace",
    "player2": "specs"
  },
  {
    "round": 4,
    "phase": 1,
    "table": 29,
    "winner": "hanaex",
    "player1": "hanaex",
    "player2": "quetzalyami"
  },
  {
    "round": 4,
    "phase": 1,
    "table": 30,
    "winner": "zholit",
    "player1": "zholit",
    "player2": "russ_ii"
  },
  {
    "round": 4,
    "phase": 1,
    "table": 31,
    "winner": "srafaelitocs",
    "player1": "srafaelitocs",
    "player2": "luffyhouz"
  },
  {
    "round": 4,
    "phase": 1,
    "table": 32,
    "winner": "luckypoke",
    "player1": "luckypoke",
    "player2": "draxoz"
  },
  {
    "round": 4,
    "phase": 1,
    "table": 33,
    "winner": "irid1um",
    "player1": "irid1um",
    "player2": "alonso39"
  },
  {
    "round": 4,
    "phase": 1,
    "table": 34,
    "winner": "n3wa",
    "player1": "n3wa",
    "player2": "bigred12121"
  },
  {
    "round": 4,
    "phase": 1,
    "table": 35,
    "winner": "popay",
    "player1": "popay",
    "player2": "alana"
  },
  {
    "round": 4,
    "phase": 1,
    "table": 36,
    "winner": "estehlegitea",
    "player1": "roshy",
    "player2": "estehlegitea"
  },
  {
    "round": 4,
    "phase": 1,
    "table": 37,
    "winner": "zeekholz",
    "player1": "zeekholz",
    "player2": "griffsama"
  },
  {
    "round": 4,
    "phase": 1,
    "table": 38,
    "winner": "disposablehero",
    "player1": "disposablehero",
    "player2": "maykol2294"
  },
  {
    "round": 4,
    "phase": 1,
    "table": 39,
    "winner": -1,
    "player1": "frogger",
    "player2": "torapapa"
  },
  {
    "round": 4,
    "phase": 1,
    "table": 40,
    "winner": "ttv_jmpm9",
    "player1": "rzlby",
    "player2": "ttv_jmpm9"
  },
  {
    "round": 4,
    "phase": 1,
    "table": 41,
    "winner": "flipinton",
    "player1": "noah2000",
    "player2": "flipinton"
  },
  {
    "round": 4,
    "phase": 1,
    "table": 42,
    "winner": -1,
    "player1": "pokehunter01",
    "player2": "ppitopin8"
  },
  {
    "round": 4,
    "phase": 1,
    "table": 43,
    "winner": "xavikush6",
    "player1": "xavikush6"
  },
  {
    "round": 5,
    "phase": 1,
    "table": 1,
    "winner": "vgckomalika",
    "player1": "vgckomalika",
    "player2": "ixerox"
  },
  {
    "round": 5,
    "phase": 1,
    "table": 2,
    "winner": "ojisanathee",
    "player1": "yuuichi",
    "player2": "ojisanathee"
  },
  {
    "round": 5,
    "phase": 1,
    "table": 3,
    "winner": "portlandpoliwags",
    "player1": "portlandpoliwags",
    "player2": "hosi"
  },
  {
    "round": 5,
    "phase": 1,
    "table": 4,
    "winner": "iplaypokemans",
    "player1": "iplaypokemans",
    "player2": "nemu"
  },
  {
    "round": 5,
    "phase": 1,
    "table": 5,
    "winner": "wxxsz",
    "player1": "vagabondwolf",
    "player2": "wxxsz"
  },
  {
    "round": 5,
    "phase": 1,
    "table": 6,
    "winner": "nandosgude",
    "player1": "tibandera",
    "player2": "nandosgude"
  },
  {
    "round": 5,
    "phase": 1,
    "table": 7,
    "winner": "cus",
    "player1": "eilix524",
    "player2": "cus"
  },
  {
    "round": 5,
    "phase": 1,
    "table": 8,
    "winner": "lightxz",
    "player1": "hectordf",
    "player2": "lightxz"
  },
  {
    "round": 5,
    "phase": 1,
    "table": 9,
    "winner": "valhar",
    "player1": "valhar",
    "player2": "njjord7"
  },
  {
    "round": 5,
    "phase": 1,
    "table": 10,
    "winner": "asura_wakr",
    "player1": "asura_wakr",
    "player2": "waterbetter"
  },
  {
    "round": 5,
    "phase": 1,
    "table": 11,
    "winner": "esdeath",
    "player1": "esdeath",
    "player2": "sawatz_1503"
  },
  {
    "round": 5,
    "phase": 1,
    "table": 12,
    "winner": "aoisora",
    "player1": "bingka",
    "player2": "aoisora"
  },
  {
    "round": 5,
    "phase": 1,
    "table": 13,
    "winner": -1,
    "player1": "soadmon",
    "player2": "julez45"
  },
  {
    "round": 5,
    "phase": 1,
    "table": 14,
    "winner": "dashmd",
    "player1": "dashmd",
    "player2": "elmatadorperu"
  },
  {
    "round": 5,
    "phase": 1,
    "table": 15,
    "winner": "wompwomp007",
    "player1": "wompwomp007",
    "player2": "turbone101"
  },
  {
    "round": 5,
    "phase": 1,
    "table": 16,
    "winner": "estehlegitea",
    "player1": "cloud77",
    "player2": "estehlegitea"
  },
  {
    "round": 5,
    "phase": 1,
    "table": 17,
    "winner": "raydorm",
    "player1": "donkindonuts",
    "player2": "raydorm"
  },
  {
    "round": 5,
    "phase": 1,
    "table": 18,
    "winner": "shikamaru_br",
    "player1": "warpis",
    "player2": "shikamaru_br"
  },
  {
    "round": 5,
    "phase": 1,
    "table": 19,
    "winner": "specs",
    "player1": "specs",
    "player2": "zholit"
  },
  {
    "round": 5,
    "phase": 1,
    "table": 20,
    "winner": "elatomico",
    "player1": "roky",
    "player2": "elatomico"
  },
  {
    "round": 5,
    "phase": 1,
    "table": 21,
    "winner": "srafaelitocs",
    "player1": "srafaelitocs",
    "player2": "sparadrap"
  },
  {
    "round": 5,
    "phase": 1,
    "table": 22,
    "winner": "raiderboy181",
    "player1": "raiderboy181",
    "player2": "raiden_shogun14"
  },
  {
    "round": 5,
    "phase": 1,
    "table": 23,
    "winner": "zeekholz",
    "player1": "nyphyx",
    "player2": "zeekholz"
  },
  {
    "round": 5,
    "phase": 1,
    "table": 24,
    "winner": "irid1um",
    "player1": "irid1um",
    "player2": "piutonium"
  },
  {
    "round": 5,
    "phase": 1,
    "table": 25,
    "winner": "popay",
    "player1": "luckypoke",
    "player2": "popay"
  },
  {
    "round": 5,
    "phase": 1,
    "table": 26,
    "winner": "ezz67",
    "player1": "goblinsama",
    "player2": "ezz67"
  },
  {
    "round": 5,
    "phase": 1,
    "table": 27,
    "winner": "disposablehero",
    "player1": "disposablehero",
    "player2": "n3wa"
  },
  {
    "round": 5,
    "phase": 1,
    "table": 28,
    "winner": "meendes",
    "player1": "meendes",
    "player2": "hiiran"
  },
  {
    "round": 5,
    "phase": 1,
    "table": 29,
    "winner": "nakopol91",
    "player1": "hanaex",
    "player2": "nakopol91"
  },
  {
    "round": 5,
    "phase": 1,
    "table": 30,
    "winner": "val22",
    "player1": "val22",
    "player2": "bredle"
  },
  {
    "round": 5,
    "phase": 1,
    "table": 31,
    "winner": "ttv_jmpm9",
    "player1": "super_peace",
    "player2": "ttv_jmpm9"
  },
  {
    "round": 5,
    "phase": 1,
    "table": 32,
    "winner": "sotrill18",
    "player1": "alonso39",
    "player2": "sotrill18"
  },
  {
    "round": 5,
    "phase": 1,
    "table": 33,
    "winner": "roshy",
    "player1": "roshy",
    "player2": "flipinton"
  },
  {
    "round": 5,
    "phase": 1,
    "table": 34,
    "winner": -1,
    "player1": "alana",
    "player2": "xavikush6"
  },
  {
    "round": 5,
    "phase": 1,
    "table": 35,
    "winner": -1,
    "player1": "luffyhouz",
    "player2": "torapapa"
  },
  {
    "round": 5,
    "phase": 1,
    "table": 36,
    "winner": -1,
    "player1": "pokehunter01",
    "player2": "rzlby"
  },
  {
    "round": 5,
    "phase": 1,
    "table": 37,
    "winner": -1,
    "player1": "ppitopin8",
    "player2": "frogger"
  },
  {
    "round": 5,
    "phase": 1,
    "table": 38,
    "winner": -1,
    "player1": "noah2000",
    "player2": "maykol2294"
  },
  {
    "round": 6,
    "phase": 1,
    "table": 1,
    "winner": "ojisanathee",
    "player1": "vgckomalika",
    "player2": "ojisanathee"
  },
  {
    "round": 6,
    "phase": 1,
    "table": 2,
    "winner": "portlandpoliwags",
    "player1": "portlandpoliwags",
    "player2": "wompwomp007"
  },
  {
    "round": 6,
    "phase": 1,
    "table": 3,
    "winner": "ixerox",
    "player1": "ixerox",
    "player2": "wxxsz"
  },
  {
    "round": 6,
    "phase": 1,
    "table": 4,
    "winner": "cus",
    "player1": "lightxz",
    "player2": "cus"
  },
  {
    "round": 6,
    "phase": 1,
    "table": 5,
    "winner": "valhar",
    "player1": "iplaypokemans",
    "player2": "valhar"
  },
  {
    "round": 6,
    "phase": 1,
    "table": 6,
    "winner": 0,
    "player1": "esdeath",
    "player2": "aoisora"
  },
  {
    "round": 6,
    "phase": 1,
    "table": 7,
    "winner": "asura_wakr",
    "player1": "asura_wakr",
    "player2": "dashmd"
  },
  {
    "round": 6,
    "phase": 1,
    "table": 8,
    "winner": "nandosgude",
    "player1": "hosi",
    "player2": "nandosgude"
  },
  {
    "round": 6,
    "phase": 1,
    "table": 9,
    "winner": "yuuichi",
    "player1": "yuuichi",
    "player2": "specs"
  },
  {
    "round": 6,
    "phase": 1,
    "table": 10,
    "winner": "estehlegitea",
    "player1": "popay",
    "player2": "estehlegitea"
  },
  {
    "round": 6,
    "phase": 1,
    "table": 11,
    "winner": "eilix524",
    "player1": "irid1um",
    "player2": "eilix524"
  },
  {
    "round": 6,
    "phase": 1,
    "table": 12,
    "winner": "elatomico",
    "player1": "hectordf",
    "player2": "elatomico"
  },
  {
    "round": 6,
    "phase": 1,
    "table": 13,
    "winner": "nakopol91",
    "player1": "nakopol91",
    "player2": "srafaelitocs"
  },
  {
    "round": 6,
    "phase": 1,
    "table": 14,
    "winner": "zeekholz",
    "player1": "raiderboy181",
    "player2": "zeekholz"
  },
  {
    "round": 6,
    "phase": 1,
    "table": 15,
    "winner": "ezz67",
    "player1": "tibandera",
    "player2": "ezz67"
  },
  {
    "round": 6,
    "phase": 1,
    "table": 16,
    "winner": "elmatadorperu",
    "player1": "njjord7",
    "player2": "elmatadorperu"
  },
  {
    "round": 6,
    "phase": 1,
    "table": 17,
    "winner": "disposablehero",
    "player1": "meendes",
    "player2": "disposablehero"
  },
  {
    "round": 6,
    "phase": 1,
    "table": 18,
    "winner": "turbone101",
    "player1": "turbone101",
    "player2": "bingka"
  },
  {
    "round": 6,
    "phase": 1,
    "table": 19,
    "winner": "vagabondwolf",
    "player1": "raydorm",
    "player2": "vagabondwolf"
  },
  {
    "round": 6,
    "phase": 1,
    "table": 20,
    "winner": "sawatz_1503",
    "player1": "sawatz_1503",
    "player2": "soadmon"
  },
  {
    "round": 6,
    "phase": 1,
    "table": 21,
    "winner": "nemu",
    "player1": "nemu",
    "player2": "waterbetter"
  },
  {
    "round": 6,
    "phase": 1,
    "table": 22,
    "winner": "val22",
    "player1": "val22",
    "player2": "shikamaru_br"
  },
  {
    "round": 6,
    "phase": 1,
    "table": 23,
    "winner": "hanaex",
    "player1": "hanaex",
    "player2": "roshy"
  },
  {
    "round": 6,
    "phase": 1,
    "table": 24,
    "winner": "n3wa",
    "player1": "goblinsama",
    "player2": "n3wa"
  },
  {
    "round": 6,
    "phase": 1,
    "table": 25,
    "winner": "nyphyx",
    "player1": "nyphyx",
    "player2": "cloud77"
  },
  {
    "round": 6,
    "phase": 1,
    "table": 26,
    "winner": "zholit",
    "player1": "donkindonuts",
    "player2": "zholit"
  },
  {
    "round": 6,
    "phase": 1,
    "table": 27,
    "winner": "luckypoke",
    "player1": "luckypoke",
    "player2": "raiden_shogun14"
  },
  {
    "round": 6,
    "phase": 1,
    "table": 28,
    "winner": "warpis",
    "player1": "warpis",
    "player2": "ttv_jmpm9"
  },
  {
    "round": 6,
    "phase": 1,
    "table": 29,
    "winner": "bredle",
    "player1": "sotrill18",
    "player2": "bredle"
  },
  {
    "round": 6,
    "phase": 1,
    "table": 30,
    "winner": -1,
    "player1": "roky",
    "player2": "luffyhouz"
  },
  {
    "round": 6,
    "phase": 1,
    "table": 31,
    "winner": -1,
    "player1": "flipinton",
    "player2": "super_peace"
  },
  {
    "round": 6,
    "phase": 1,
    "table": 32,
    "winner": -1,
    "player1": "alonso39",
    "player2": "xavikush6"
  },
  {
    "round": 6,
    "phase": 1,
    "table": 33,
    "winner": -1,
    "player1": "rzlby",
    "player2": "maykol2294"
  },
  {
    "round": 6,
    "phase": 1,
    "table": 34,
    "winner": -1,
    "player1": "frogger",
    "player2": "pokehunter01"
  },
  {
    "round": 6,
    "phase": 1,
    "table": 35,
    "winner": -1,
    "player1": "ppitopin8",
    "player2": "torapapa"
  },
  {
    "round": 6,
    "phase": 1,
    "table": 36,
    "winner": "noah2000",
    "player1": "noah2000"
  },
  {
    "round": 7,
    "phase": 1,
    "table": 1,
    "winner": "ojisanathee",
    "player1": "ojisanathee",
    "player2": "portlandpoliwags"
  },
  {
    "round": 7,
    "phase": 1,
    "table": 2,
    "winner": "asura_wakr",
    "player1": "ixerox",
    "player2": "asura_wakr"
  },
  {
    "round": 7,
    "phase": 1,
    "table": 3,
    "winner": 0,
    "player1": "vgckomalika",
    "player2": "nandosgude"
  },
  {
    "round": 7,
    "phase": 1,
    "table": 4,
    "winner": 0,
    "player1": "valhar",
    "player2": "yuuichi"
  },
  {
    "round": 7,
    "phase": 1,
    "table": 5,
    "winner": 0,
    "player1": "cus",
    "player2": "aoisora"
  },
  {
    "round": 7,
    "phase": 1,
    "table": 6,
    "winner": "vagabondwolf",
    "player1": "esdeath",
    "player2": "vagabondwolf"
  },
  {
    "round": 7,
    "phase": 1,
    "table": 7,
    "winner": 0,
    "player1": "estehlegitea",
    "player2": "wxxsz"
  },
  {
    "round": 7,
    "phase": 1,
    "table": 8,
    "winner": "lightxz",
    "player1": "ezz67",
    "player2": "lightxz"
  },
  {
    "round": 7,
    "phase": 1,
    "table": 9,
    "winner": 0,
    "player1": "nemu",
    "player2": "val22"
  },
  {
    "round": 7,
    "phase": 1,
    "table": 10,
    "winner": "nakopol91",
    "player1": "elatomico",
    "player2": "nakopol91"
  },
  {
    "round": 7,
    "phase": 1,
    "table": 11,
    "winner": "eilix524",
    "player1": "iplaypokemans",
    "player2": "eilix524"
  },
  {
    "round": 7,
    "phase": 1,
    "table": 12,
    "winner": 0,
    "player1": "elmatadorperu",
    "player2": "disposablehero"
  },
  {
    "round": 7,
    "phase": 1,
    "table": 13,
    "winner": "dashmd",
    "player1": "turbone101",
    "player2": "dashmd"
  },
  {
    "round": 7,
    "phase": 1,
    "table": 14,
    "winner": "hosi",
    "player1": "sawatz_1503",
    "player2": "hosi"
  },
  {
    "round": 7,
    "phase": 1,
    "table": 15,
    "winner": 0,
    "player1": "wompwomp007",
    "player2": "zeekholz"
  },
  {
    "round": 7,
    "phase": 1,
    "table": 16,
    "winner": "luckypoke",
    "player1": "luckypoke",
    "player2": "hanaex"
  },
  {
    "round": 7,
    "phase": 1,
    "table": 17,
    "winner": "nyphyx",
    "player1": "nyphyx",
    "player2": "bredle"
  },
  {
    "round": 7,
    "phase": 1,
    "table": 18,
    "winner": "shikamaru_br",
    "player1": "meendes",
    "player2": "shikamaru_br"
  },
  {
    "round": 7,
    "phase": 1,
    "table": 19,
    "winner": "waterbetter",
    "player1": "n3wa",
    "player2": "waterbetter"
  },
  {
    "round": 7,
    "phase": 1,
    "table": 20,
    "winner": "warpis",
    "player1": "njjord7",
    "player2": "warpis"
  },
  {
    "round": 7,
    "phase": 1,
    "table": 21,
    "winner": "zholit",
    "player1": "zholit",
    "player2": "bingka"
  },
  {
    "round": 7,
    "phase": 1,
    "table": 22,
    "winner": "specs",
    "player1": "tibandera",
    "player2": "specs"
  },
  {
    "round": 7,
    "phase": 1,
    "table": 23,
    "winner": "srafaelitocs",
    "player1": "srafaelitocs",
    "player2": "popay"
  },
  {
    "round": 7,
    "phase": 1,
    "table": 24,
    "winner": "raiderboy181",
    "player1": "raiderboy181",
    "player2": "roshy"
  },
  {
    "round": 7,
    "phase": 1,
    "table": 25,
    "winner": "goblinsama",
    "player1": "goblinsama",
    "player2": "cloud77"
  },
  {
    "round": 7,
    "phase": 1,
    "table": 26,
    "winner": "raiden_shogun14",
    "player1": "raiden_shogun14",
    "player2": "xavikush6"
  },
  {
    "round": 7,
    "phase": 1,
    "table": 27,
    "winner": -1,
    "player1": "flipinton",
    "player2": "donkindonuts"
  },
  {
    "round": 7,
    "phase": 1,
    "table": 28,
    "winner": "luffyhouz",
    "player1": "luffyhouz"
  },
  {
    "phase": 2,
    "round": 8,
    "winner": "wxxsz",
    "match": "T32-10",
    "player1": "aoisora",
    "player2": "wxxsz"
  },
  {
    "phase": 2,
    "round": 8,
    "winner": "estehlegitea",
    "match": "T8-4",
    "player1": "asura_wakr",
    "player2": "estehlegitea"
  },
  {
    "phase": 2,
    "round": 8,
    "winner": "asura_wakr",
    "match": "T16-7",
    "player1": "asura_wakr",
    "player2": "vagabondwolf"
  },
  {
    "phase": 2,
    "round": 8,
    "winner": "asura_wakr",
    "match": "T32-13",
    "player1": "asura_wakr",
    "player2": "ezz67"
  },
  {
    "phase": 2,
    "round": 8,
    "winner": "nemu",
    "match": "T32-6",
    "player1": "lightxz",
    "player2": "nemu"
  },
  {
    "phase": 2,
    "round": 8,
    "winner": "estehlegitea",
    "match": "T16-8",
    "player1": "sawatz_1503",
    "player2": "estehlegitea"
  },
  {
    "phase": 2,
    "round": 8,
    "winner": "ixerox",
    "match": "T32-4",
    "player1": "ixerox",
    "player2": "disposablehero"
  },
  {
    "phase": 2,
    "round": 8,
    "winner": "estehlegitea",
    "match": "T32-16",
    "player1": "nakopol91",
    "player2": "estehlegitea"
  },
  {
    "phase": 2,
    "round": 8,
    "winner": "elmatadorperu",
    "match": "T32-12",
    "player1": "dashmd",
    "player2": "elmatadorperu"
  },
  {
    "phase": 2,
    "round": 8,
    "winner": "hosi",
    "match": "T4-1",
    "player1": "hosi",
    "player2": "turbone101"
  },
  {
    "phase": 2,
    "round": 8,
    "winner": "hosi",
    "match": "T8-1",
    "player1": "esdeath",
    "player2": "hosi"
  },
  {
    "phase": 2,
    "round": 8,
    "winner": "eilix524",
    "match": "T16-4",
    "player1": "specs",
    "player2": "eilix524"
  },
  {
    "phase": 2,
    "round": 8,
    "winner": "elmatadorperu",
    "match": "T8-3",
    "player1": "portlandpoliwags",
    "player2": "elmatadorperu"
  },
  {
    "phase": 2,
    "round": 8,
    "winner": "esdeath",
    "match": "T16-1",
    "player1": "srafaelitocs",
    "player2": "esdeath"
  },
  {
    "phase": 2,
    "round": 8,
    "winner": "portlandpoliwags",
    "match": "T16-5",
    "player1": "portlandpoliwags",
    "player2": "wxxsz"
  },
  {
    "phase": 2,
    "round": 8,
    "winner": "portlandpoliwags",
    "match": "T32-9",
    "player1": "portlandpoliwags",
    "player2": "zholit"
  },
  {
    "phase": 2,
    "round": 8,
    "winner": "hosi",
    "match": "T32-3",
    "player1": "hosi",
    "player2": "iplaypokemans"
  },
  {
    "phase": 2,
    "round": 8,
    "winner": "elmatadorperu",
    "match": "T4-2",
    "player1": "elmatadorperu",
    "player2": "estehlegitea"
  },
  {
    "phase": 2,
    "round": 8,
    "winner": "hosi",
    "match": "T16-2",
    "player1": "hosi",
    "player2": "ixerox"
  },
  {
    "phase": 2,
    "round": 8,
    "winner": "eilix524",
    "match": "T32-8",
    "player1": "eilix524",
    "player2": "zeekholz"
  },
  {
    "phase": 2,
    "round": 8,
    "winner": "nandosgude",
    "match": "T32-11",
    "player1": "nandosgude",
    "player2": "waterbetter"
  },
  {
    "phase": 2,
    "round": 8,
    "winner": "hosi",
    "match": "T2-1",
    "player1": "hosi",
    "player2": "elmatadorperu"
  },
  {
    "phase": 2,
    "round": 8,
    "winner": "srafaelitocs",
    "match": "T32-1",
    "player1": "ojisanathee",
    "player2": "srafaelitocs"
  },
  {
    "phase": 2,
    "round": 8,
    "winner": "turbone101",
    "match": "T16-3",
    "player1": "turbone101",
    "player2": "nemu"
  },
  {
    "phase": 2,
    "round": 8,
    "winner": "turbone101",
    "match": "T8-2",
    "player1": "turbone101",
    "player2": "eilix524"
  },
  {
    "phase": 2,
    "round": 8,
    "winner": "vagabondwolf",
    "match": "T32-14",
    "player1": "vagabondwolf",
    "player2": "wompwomp007"
  },
  {
    "phase": 2,
    "round": 8,
    "winner": "esdeath",
    "match": "T32-2",
    "player1": "val22",
    "player2": "esdeath"
  },
  {
    "phase": 2,
    "round": 8,
    "winner": "specs",
    "match": "T32-7",
    "player1": "valhar",
    "player2": "specs"
  },
  {
    "phase": 2,
    "round": 8,
    "winner": "turbone101",
    "match": "T32-5",
    "player1": "vgckomalika",
    "player2": "turbone101"
  },
  {
    "phase": 2,
    "round": 8,
    "winner": "sawatz_1503",
    "match": "T32-15",
    "player1": "cus",
    "player2": "sawatz_1503"
  },
  {
    "phase": 2,
    "round": 8,
    "winner": "elmatadorperu",
    "match": "T16-6",
    "player1": "nandosgude",
    "player2": "elmatadorperu"
  }
]