[
  {
    "round": 1,
    "phase": 1,
    "table": null,
    "winner": -1,
    "player1": "xxdarkxx"
  },
  {
    "round": 1,
    "phase": 1,
    "table": null,
    "winner": -1,
    "player1": "kpenter"
  },
  {
    "round": 1,
    "phase": 1,
    "table": null,
    "winner": -1,
    "player1": "thebulldaver9"
  },
  {
    "round": 1,
    "phase": 1,
    "table": null,
    "winner": -1,
    "player1": "cargs"
  },
  {
    "round": 1,
    "phase": 1,
    "table": 1,
    "winner": "avidist",
    "player1": "ezmiker",
    "player2": "avidist"
  },
  {
    "round": 1,
    "phase": 1,
    "table": 2,
    "winner": "sadiearmour05",
    "player1": "sadiearmour05",
    "player2": "el_cable"
  },
  {
    "round": 1,
    "phase": 1,
    "table": 3,
    "winner": "calebwjordan",
    "player1": "calebwjordan",
    "player2": "luckycrow89"
  },
  {
    "round": 1,
    "phase": 1,
    "table": 4,
    "winner": "asian_lano",
    "player1": "guitarspear",
    "player2": "asian_lano"
  },
  {
    "round": 1,
    "phase": 1,
    "table": 5,
    "winner": "lanz",
    "player1": "jojotheklown",
    "player2": "lanz"
  },
  {
    "round": 1,
    "phase": 1,
    "table": 6,
    "winner": "eazycheeze",
    "player1": "eazycheeze",
    "player2": "judesalinas"
  },
  {
    "round": 1,
    "phase": 1,
    "table": 7,
    "winner": "savid400",
    "player1": "savid400",
    "player2": "pokejorji"
  },
  {
    "round": 1,
    "phase": 1,
    "table": 8,
    "winner": "gholdengo_ex",
    "player1": "gholdengo_ex",
    "player2": "indirectswing89"
  },
  {
    "round": 1,
    "phase": 1,
    "table": 9,
    "winner": "pikalu",
    "player1": "mark5kp",
    "player2": "pikalu"
  },
  {
    "round": 1,
    "phase": 1,
    "table": 10,
    "winner": "jpthereal",
    "player1": "t2tcg",
    "player2": "jpthereal"
  },
  {
    "round": 1,
    "phase": 1,
    "table": 11,
    "winner": "chefchino",
    "player1": "chefchino",
    "player2": "wwwdiocane_it"
  },
  {
    "round": 1,
    "phase": 1,
    "table": 12,
    "winner": "brandodo2",
    "player1": "brandodo2",
    "player2": "lnmastodon"
  },
  {
    "round": 1,
    "phase": 1,
    "table": 13,
    "winner": "dianabrand",
    "player1": "joniiecheerios",
    "player2": "dianabrand"
  },
  {
    "round": 1,
    "phase": 1,
    "table": 14,
    "winner": "mollyjomy",
    "player1": "mollyjomy",
    "player2": "ante_nurse"
  },
  {
    "round": 1,
    "phase": 1,
    "table": 15,
    "winner": "snipwe27",
    "player1": "elliedark",
    "player2": "snipwe27"
  },
  {
    "round": 1,
    "phase": 1,
    "table": 16,
    "winner": "foodking90",
    "player1": "poffination",
    "player2": "foodking90"
  },
  {
    "round": 1,
    "phase": 1,
    "table": 17,
    "winner": "captainbean8",
    "player1": "kawikibosh86",
    "player2": "captainbean8"
  },
  {
    "round": 1,
    "phase": 1,
    "table": 18,
    "winner": "xgavh",
    "player1": "xgavh",
    "player2": "rahmat"
  },
  {
    "round": 1,
    "phase": 1,
    "table": 19,
    "winner": "ciwangeptcg",
    "player1": "treetrunks",
    "player2": "ciwangeptcg"
  },
  {
    "round": 1,
    "phase": 1,
    "table": 20,
    "winner": "herm4n0",
    "player1": "herm4n0",
    "player2": "pupitar"
  },
  {
    "round": 1,
    "phase": 1,
    "table": 21,
    "winner": "maxwellm101202",
    "player1": "shrekster9000",
    "player2": "maxwellm101202"
  },
  {
    "round": 2,
    "phase": 1,
    "table": null,
    "winner": -1,
    "player1": "xxdarkxx"
  },
  {
    "round": 2,
    "phase": 1,
    "table": 1,
    "winner": "mollyjomy",
    "player1": "asian_lano",
    "player2": "mollyjomy"
  },
  {
    "round": 2,
    "phase": 1,
    "table": 2,
    "winner": "foodking90",
    "player1": "foodking90",
    "player2": "eazycheeze"
  },
  {
    "round": 2,
    "phase": 1,
    "table": 3,
    "winner": "jpthereal",
    "player1": "sadiearmour05",
    "player2": "jpthereal"
  },
  {
    "round": 2,
    "phase": 1,
    "table": 4,
    "winner": "snipwe27",
    "player1": "chefchino",
    "player2": "snipwe27"
  },
  {
    "round": 2,
    "phase": 1,
    "table": 5,
    "winner": "maxwellm101202",
    "player1": "dianabrand",
    "player2": "maxwellm101202"
  },
  {
    "round": 2,
    "phase": 1,
    "table": 6,
    "winner": "herm4n0",
    "player1": "herm4n0",
    "player2": "captainbean8"
  },
  {
    "round": 2,
    "phase": 1,
    "table": 7,
    "winner": "ciwangeptcg",
    "player1": "ciwangeptcg",
    "player2": "calebwjordan"
  },
  {
    "round": 2,
    "phase": 1,
    "table": 8,
    "winner": "lanz",
    "player1": "xgavh",
    "player2": "lanz"
  },
  {
    "round": 2,
    "phase": 1,
    "table": 9,
    "winner": "pikalu",
    "player1": "pikalu",
    "player2": "gholdengo_ex"
  },
  {
    "round": 2,
    "phase": 1,
    "table": 10,
    "winner": "avidist",
    "player1": "brandodo2",
    "player2": "avidist"
  },
  {
    "round": 2,
    "phase": 1,
    "table": 11,
    "winner": "savid400",
    "player1": "savid400",
    "player2": "rahmat"
  },
  {
    "round": 2,
    "phase": 1,
    "table": 12,
    "winner": "shrekster9000",
    "player1": "shrekster9000",
    "player2": "kawikibosh86"
  },
  {
    "round": 2,
    "phase": 1,
    "table": 13,
    "winner": "poffination",
    "player1": "poffination",
    "player2": "kpenter"
  },
  {
    "round": 2,
    "phase": 1,
    "table": 14,
    "winner": "wwwdiocane_it",
    "player1": "wwwdiocane_it",
    "player2": "cargs"
  },
  {
    "round": 2,
    "phase": 1,
    "table": 15,
    "winner": "pokejorji",
    "player1": "pokejorji",
    "player2": "judesalinas"
  },
  {
    "round": 2,
    "phase": 1,
    "table": 16,
    "winner": "joniiecheerios",
    "player1": "joniiecheerios",
    "player2": "mark5kp"
  },
  {
    "round": 2,
    "phase": 1,
    "table": 17,
    "winner": "jojotheklown",
    "player1": "jojotheklown",
    "player2": "guitarspear"
  },
  {
    "round": 2,
    "phase": 1,
    "table": 18,
    "winner": "pupitar",
    "player1": "pupitar",
    "player2": "el_cable"
  },
  {
    "round": 3,
    "phase": 1,
    "table": 1,
    "winner": "jpthereal",
    "player1": "jpthereal",
    "player2": "mollyjomy"
  },
  {
    "round": 3,
    "phase": 1,
    "table": 2,
    "winner": "savid400",
    "player1": "snipwe27",
    "player2": "savid400"
  },
  {
    "round": 3,
    "phase": 1,
    "table": 3,
    "winner": "maxwellm101202",
    "player1": "maxwellm101202",
    "player2": "herm4n0"
  },
  {
    "round": 3,
    "phase": 1,
    "table": 4,
    "winner": "pikalu",
    "player1": "pikalu",
    "player2": "ciwangeptcg"
  },
  {
    "round": 3,
    "phase": 1,
    "table": 5,
    "winner": "foodking90",
    "player1": "lanz",
    "player2": "foodking90"
  },
  {
    "round": 3,
    "phase": 1,
    "table": 6,
    "winner": "avidist",
    "player1": "avidist",
    "player2": "eazycheeze"
  },
  {
    "round": 3,
    "phase": 1,
    "table": 7,
    "winner": "chefchino",
    "player1": "sadiearmour05",
    "player2": "chefchino"
  },
  {
    "round": 3,
    "phase": 1,
    "table": 8,
    "winner": "jojotheklown",
    "player1": "jojotheklown",
    "player2": "brandodo2"
  },
  {
    "round": 3,
    "phase": 1,
    "table": 9,
    "winner": "joniiecheerios",
    "player1": "joniiecheerios",
    "player2": "captainbean8"
  },
  {
    "round": 3,
    "phase": 1,
    "table": 10,
    "winner": "gholdengo_ex",
    "player1": "pupitar",
    "player2": "gholdengo_ex"
  },
  {
    "round": 3,
    "phase": 1,
    "table": 11,
    "winner": "calebwjordan",
    "player1": "poffination",
    "player2": "calebwjordan"
  },
  {
    "round": 3,
    "phase": 1,
    "table": 12,
    "winner": "pokejorji",
    "player1": "xgavh",
    "player2": "pokejorji"
  },
  {
    "round": 3,
    "phase": 1,
    "table": 13,
    "winner": "shrekster9000",
    "player1": "shrekster9000",
    "player2": "wwwdiocane_it"
  },
  {
    "round": 3,
    "phase": 1,
    "table": 14,
    "winner": "kawikibosh86",
    "player1": "dianabrand",
    "player2": "kawikibosh86"
  },
  {
    "round": 3,
    "phase": 1,
    "table": 15,
    "winner": -1,
    "player1": "rahmat",
    "player2": "cargs"
  },
  {
    "round": 3,
    "phase": 1,
    "table": 16,
    "winner": "kpenter",
    "player1": "kpenter",
    "player2": "xxdarkxx"
  },
  {
    "round": 3,
    "phase": 1,
    "table": 17,
    "winner": "mark5kp",
    "player1": "mark5kp"
  },
  {
    "round": 4,
    "phase": 1,
    "table": 1,
    "winner": "avidist",
    "player1": "avidist",
    "player2": "foodking90"
  },
  {
    "round": 4,
    "phase": 1,
    "table": 2,
    "winner": "savid400",
    "player1": "savid400",
    "player2": "jpthereal"
  },
  {
    "round": 4,
    "phase": 1,
    "table": 3,
    "winner": "maxwellm101202",
    "player1": "pikalu",
    "player2": "maxwellm101202"
  },
  {
    "round": 4,
    "phase": 1,
    "table": 4,
    "winner": "joniiecheerios",
    "player1": "joniiecheerios",
    "player2": "shrekster9000"
  },
  {
    "round": 4,
    "phase": 1,
    "table": 5,
    "winner": "herm4n0",
    "player1": "pokejorji",
    "player2": "herm4n0"
  },
  {
    "round": 4,
    "phase": 1,
    "table": 6,
    "winner": "snipwe27",
    "player1": "snipwe27",
    "player2": "mollyjomy"
  },
  {
    "round": 4,
    "phase": 1,
    "table": 7,
    "winner": "jojotheklown",
    "player1": "ciwangeptcg",
    "player2": "jojotheklown"
  },
  {
    "round": 4,
    "phase": 1,
    "table": 8,
    "winner": "calebwjordan",
    "player1": "chefchino",
    "player2": "calebwjordan"
  },
  {
    "round": 4,
    "phase": 1,
    "table": 9,
    "winner": "kawikibosh86",
    "player1": "kawikibosh86",
    "player2": "mark5kp"
  },
  {
    "round": 4,
    "phase": 1,
    "table": 10,
    "winner": "dianabrand",
    "player1": "dianabrand",
    "player2": "eazycheeze"
  },
  {
    "round": 4,
    "phase": 1,
    "table": 11,
    "winner": "kpenter",
    "player1": "kpenter",
    "player2": "cargs"
  },
  {
    "round": 4,
    "phase": 1,
    "table": 12,
    "winner": "captainbean8",
    "player1": "captainbean8",
    "player2": "xgavh"
  },
  {
    "round": 4,
    "phase": 1,
    "table": 13,
    "winner": "rahmat",
    "player1": "rahmat"
  },
  {
    "round": 5,
    "phase": 1,
    "table": 1,
    "winner": "avidist",
    "player1": "avidist",
    "player2": "savid400"
  },
  {
    "round": 5,
    "phase": 1,
    "table": 2,
    "winner": "maxwellm101202",
    "player1": "maxwellm101202",
    "player2": "jpthereal"
  },
  {
    "round": 5,
    "phase": 1,
    "table": 3,
    "winner": "snipwe27",
    "player1": "calebwjordan",
    "player2": "snipwe27"
  },
  {
    "round": 5,
    "phase": 1,
    "table": 4,
    "winner": "jojotheklown",
    "player1": "joniiecheerios",
    "player2": "jojotheklown"
  },
  {
    "round": 5,
    "phase": 1,
    "table": 5,
    "winner": "pikalu",
    "player1": "pikalu",
    "player2": "herm4n0"
  },
  {
    "round": 5,
    "phase": 1,
    "table": 6,
    "winner": "ciwangeptcg",
    "player1": "dianabrand",
    "player2": "ciwangeptcg"
  },
  {
    "round": 5,
    "phase": 1,
    "table": 7,
    "winner": "kawikibosh86",
    "player1": "kawikibosh86",
    "player2": "mollyjomy"
  },
  {
    "round": 5,
    "phase": 1,
    "table": 8,
    "winner": "captainbean8",
    "player1": "captainbean8",
    "player2": "shrekster9000"
  },
  {
    "round": 5,
    "phase": 1,
    "table": 9,
    "winner": "kpenter",
    "player1": "kpenter",
    "player2": "pokejorji"
  },
  {
    "round": 5,
    "phase": 1,
    "table": 10,
    "winner": "chefchino",
    "player1": "chefchino",
    "player2": "mark5kp"
  },
  {
    "round": 5,
    "phase": 1,
    "table": 11,
    "winner": -1,
    "player1": "rahmat",
    "player2": "eazycheeze"
  },
  {
    "round": 5,
    "phase": 1,
    "table": 12,
    "winner": "cargs",
    "player1": "cargs"
  }
]